qtemplate/__init__.py
qtemplate-0.0.1.dist-info/LICENSE
qtemplate-0.0.1.dist-info/METADATA
qtemplate-0.0.1.dist-info/WHEEL
qtemplate-0.0.1.dist-info/top_level.txt
qtemplate-0.0.1.dist-info/RECORD
