Metadata-Version: 2.1
Name: qtemplate
Version: 0.0.1
Summary: Flexible and extensible templating CLI
Home-page: https://github.com/QsonLabs/qtemplate
Author: Chris O'Connor
License: Apache License 2.0
Platform: UNKNOWN
Classifier: Development Status :: 1 - Planning
Classifier: Framework :: Flake8
Classifier: Framework :: tox
Classifier: License :: OSI Approved :: Apache Software License
Classifier: Operating System :: MacOS :: MacOS X
Classifier: Operating System :: POSIX :: Linux
Classifier: Operating System :: Unix
Classifier: Programming Language :: Python :: 3.7
Classifier: Programming Language :: Python :: 3.8
Requires-Dist: pyyaml
Requires-Dist: jinja2
